MANIFEST.in
README.md
setup.cfg
setup.py
TOPSIS_Razik_101803178/topsis.py
TOPSIS_Razik_101803178.egg-info/PKG-INFO
TOPSIS_Razik_101803178.egg-info/SOURCES.txt
TOPSIS_Razik_101803178.egg-info/dependency_links.txt
TOPSIS_Razik_101803178.egg-info/entry_points.txt
TOPSIS_Razik_101803178.egg-info/requires.txt
TOPSIS_Razik_101803178.egg-info/top_level.txt